pracci/__init__.py
pracci/calculator.py
pracci-0.1.0.dist-info/METADATA
pracci-0.1.0.dist-info/WHEEL
pracci-0.1.0.dist-info/RECORD
